[
  {
    "design_code": "page1-img1_png",
    "category": null,
    "style": null,
    "image": "/images/designs/page1-img1.png"
  },
  {
    "design_code": "page1-img2_jpeg",
    "category": null,
    "style": null,
    "image": "/images/designs/page1-img2.jpeg"
  },
  {
    "design_code": "page1-img3_jpeg",
    "category": null,
    "style": null,
    "image": "/images/designs/page1-img3.jpeg"
  },
  {
    "design_code": "page1-img4_jpeg",
    "category": null,
    "style": null,
    "image": "/images/designs/page1-img4.jpeg"
  },
  {
    "design_code": "page1-img5_jpeg",
    "category": null,
    "style": null,
    "image": "/images/designs/page1-img5.jpeg"
  },
  {
    "design_code": "page1-img6_jpeg",
    "category": null,
    "style": null,
    "image": "/images/designs/page1-img6.jpeg"
  },
  {
    "design_code": "page1-img7_jpeg",
    "category": null,
    "style": null,
    "image": "/images/designs/page1-img7.jpeg"
  },
  {
    "design_code": "page1-img8_jpeg",
    "category": null,
    "style": null,
    "image": "/images/designs/page1-img8.jpeg"
  },
  {
    "design_code": "page1-img9_jpeg",
    "category": null,
    "style": null,
    "image": "/images/designs/page1-img9.jpeg"
  },
  {
    "design_code": "page1-img10_jpeg",
    "category": null,
    "style": null,
    "image": "/images/designs/page1-img10.jpeg"
  },
  {
    "design_code": "page1-img11_jpeg",
    "category": null,
    "style": null,
    "image": "/images/designs/page1-img11.jpeg"
  },
  {
    "design_code": "page1-img12_png",
    "category": null,
    "style": null,
    "image": "/images/designs/page1-img12.png"
  },
  {
    "design_code": "page1-img13_jpeg",
    "category": null,
    "style": null,
    "image": "/images/designs/page1-img13.jpeg"
  },
  {
    "design_code": "page2-img1_png",
    "category": null,
    "style": null,
    "image": "/images/designs/page2-img1.png"
  },
  {
    "design_code": "page2-img2_jpeg",
    "category": null,
    "style": null,
    "image": "/images/designs/page2-img2.jpeg"
  },
  {
    "design_code": "page2-img3_jpeg",
    "category": null,
    "style": null,
    "image": "/images/designs/page2-img3.jpeg"
  },
  {
    "design_code": "page2-img4_jpeg",
    "category": null,
    "style": null,
    "image": "/images/designs/page2-img4.jpeg"
  },
  {
    "design_code": "page2-img5_jpeg",
    "category": null,
    "style": null,
    "image": "/images/designs/page2-img5.jpeg"
  },
  {
    "design_code": "page2-img6_jpeg",
    "category": null,
    "style": null,
    "image": "/images/designs/page2-img6.jpeg"
  },
  {
    "design_code": "page2-img7_jpeg",
    "category": null,
    "style": null,
    "image": "/images/designs/page2-img7.jpeg"
  },
  {
    "design_code": "page2-img8_jpeg",
    "category": null,
    "style": null,
    "image": "/images/designs/page2-img8.jpeg"
  },
  {
    "design_code": "page2-img9_jpeg",
    "category": null,
    "style": null,
    "image": "/images/designs/page2-img9.jpeg"
  },
  {
    "design_code": "page2-img10_jpeg",
    "category": null,
    "style": null,
    "image": "/images/designs/page2-img10.jpeg"
  },
  {
    "design_code": "page2-img11_jpeg",
    "category": null,
    "style": null,
    "image": "/images/designs/page2-img11.jpeg"
  },
  {
    "design_code": "page2-img12_jpeg",
    "category": null,
    "style": null,
    "image": "/images/designs/page2-img12.jpeg"
  },
  {
    "design_code": "page2-img13_jpeg",
    "category": null,
    "style": null,
    "image": "/images/designs/page2-img13.jpeg"
  },
  {
    "design_code": "page2-img14_jpeg",
    "category": null,
    "style": null,
    "image": "/images/designs/page2-img14.jpeg"
  },
  {
    "design_code": "page3-img1_jpeg",
    "category": null,
    "style": null,
    "image": "/images/designs/page3-img1.jpeg"
  },
  {
    "design_code": "page3-img2_jpeg",
    "category": null,
    "style": null,
    "image": "/images/designs/page3-img2.jpeg"
  },
  {
    "design_code": "page3-img3_jpeg",
    "category": null,
    "style": null,
    "image": "/images/designs/page3-img3.jpeg"
  },
  {
    "design_code": "page3-img4_jpeg",
    "category": null,
    "style": null,
    "image": "/images/designs/page3-img4.jpeg"
  },
  {
    "design_code": "page3-img5_jpeg",
    "category": null,
    "style": null,
    "image": "/images/designs/page3-img5.jpeg"
  },
  {
    "design_code": "page3-img6_jpeg",
    "category": null,
    "style": null,
    "image": "/images/designs/page3-img6.jpeg"
  },
  {
    "design_code": "page3-img7_jpeg",
    "category": null,
    "style": null,
    "image": "/images/designs/page3-img7.jpeg"
  },
  {
    "design_code": "page3-img8_jpeg",
    "category": null,
    "style": null,
    "image": "/images/designs/page3-img8.jpeg"
  },
  {
    "design_code": "page3-img9_jpeg",
    "category": null,
    "style": null,
    "image": "/images/designs/page3-img9.jpeg"
  },
  {
    "design_code": "page3-img10_jpeg",
    "category": null,
    "style": null,
    "image": "/images/designs/page3-img10.jpeg"
  },
  {
    "design_code": "page3-img11_jpeg",
    "category": null,
    "style": null,
    "image": "/images/designs/page3-img11.jpeg"
  },
  {
    "design_code": "page3-img12_jpeg",
    "category": null,
    "style": null,
    "image": "/images/designs/page3-img12.jpeg"
  },
  {
    "design_code": "page3-img13_jpeg",
    "category": null,
    "style": null,
    "image": "/images/designs/page3-img13.jpeg"
  },
  {
    "design_code": "page3-img14_jpeg",
    "category": null,
    "style": null,
    "image": "/images/designs/page3-img14.jpeg"
  },
  {
    "design_code": "page3-img15_jpeg",
    "category": null,
    "style": null,
    "image": "/images/designs/page3-img15.jpeg"
  },
  {
    "design_code": "page3-img16_jpeg",
    "category": null,
    "style": null,
    "image": "/images/designs/page3-img16.jpeg"
  },
  {
    "design_code": "page4-img1_jpeg",
    "category": null,
    "style": null,
    "image": "/images/designs/page4-img1.jpeg"
  },
  {
    "design_code": "page4-img2_jpeg",
    "category": null,
    "style": null,
    "image": "/images/designs/page4-img2.jpeg"
  },
  {
    "design_code": "page4-img3_jpeg",
    "category": null,
    "style": null,
    "image": "/images/designs/page4-img3.jpeg"
  },
  {
    "design_code": "page4-img4_jpeg",
    "category": null,
    "style": null,
    "image": "/images/designs/page4-img4.jpeg"
  },
  {
    "design_code": "page4-img5_jpeg",
    "category": null,
    "style": null,
    "image": "/images/designs/page4-img5.jpeg"
  },
  {
    "design_code": "page4-img6_jpeg",
    "category": null,
    "style": null,
    "image": "/images/designs/page4-img6.jpeg"
  },
  {
    "design_code": "page4-img7_jpeg",
    "category": null,
    "style": null,
    "image": "/images/designs/page4-img7.jpeg"
  },
  {
    "design_code": "page4-img8_jpeg",
    "category": null,
    "style": null,
    "image": "/images/designs/page4-img8.jpeg"
  },
  {
    "design_code": "page4-img9_jpeg",
    "category": null,
    "style": null,
    "image": "/images/designs/page4-img9.jpeg"
  },
  {
    "design_code": "page4-img10_jpeg",
    "category": null,
    "style": null,
    "image": "/images/designs/page4-img10.jpeg"
  },
  {
    "design_code": "page4-img11_jpeg",
    "category": null,
    "style": null,
    "image": "/images/designs/page4-img11.jpeg"
  },
  {
    "design_code": "page4-img12_jpeg",
    "category": null,
    "style": null,
    "image": "/images/designs/page4-img12.jpeg"
  },
  {
    "design_code": "page4-img13_jpeg",
    "category": null,
    "style": null,
    "image": "/images/designs/page4-img13.jpeg"
  },
  {
    "design_code": "page4-img14_jpeg",
    "category": null,
    "style": null,
    "image": "/images/designs/page4-img14.jpeg"
  },
  {
    "design_code": "page4-img15_jpeg",
    "category": null,
    "style": null,
    "image": "/images/designs/page4-img15.jpeg"
  },
  {
    "design_code": "page4-img16_jpeg",
    "category": null,
    "style": null,
    "image": "/images/designs/page4-img16.jpeg"
  },
  {
    "design_code": "page4-img17_jpeg",
    "category": null,
    "style": null,
    "image": "/images/designs/page4-img17.jpeg"
  },
  {
    "design_code": "page4-img18_jpeg",
    "category": null,
    "style": null,
    "image": "/images/designs/page4-img18.jpeg"
  },
  {
    "design_code": "page4-img19_jpeg",
    "category": null,
    "style": null,
    "image": "/images/designs/page4-img19.jpeg"
  },
  {
    "design_code": "page4-img20_jpeg",
    "category": null,
    "style": null,
    "image": "/images/designs/page4-img20.jpeg"
  },
  {
    "design_code": "page5-img1_jpeg",
    "category": null,
    "style": null,
    "image": "/images/designs/page5-img1.jpeg"
  },
  {
    "design_code": "page5-img2_jpeg",
    "category": null,
    "style": null,
    "image": "/images/designs/page5-img2.jpeg"
  },
  {
    "design_code": "page5-img3_jpeg",
    "category": null,
    "style": null,
    "image": "/images/designs/page5-img3.jpeg"
  },
  {
    "design_code": "page5-img4_jpeg",
    "category": null,
    "style": null,
    "image": "/images/designs/page5-img4.jpeg"
  },
  {
    "design_code": "page5-img5_jpeg",
    "category": null,
    "style": null,
    "image": "/images/designs/page5-img5.jpeg"
  },
  {
    "design_code": "page5-img6_jpeg",
    "category": null,
    "style": null,
    "image": "/images/designs/page5-img6.jpeg"
  },
  {
    "design_code": "page5-img7_jpeg",
    "category": null,
    "style": null,
    "image": "/images/designs/page5-img7.jpeg"
  },
  {
    "design_code": "page5-img8_jpeg",
    "category": null,
    "style": null,
    "image": "/images/designs/page5-img8.jpeg"
  },
  {
    "design_code": "page5-img9_jpeg",
    "category": null,
    "style": null,
    "image": "/images/designs/page5-img9.jpeg"
  },
  {
    "design_code": "page5-img10_jpeg",
    "category": null,
    "style": null,
    "image": "/images/designs/page5-img10.jpeg"
  },
  {
    "design_code": "page5-img11_jpeg",
    "category": null,
    "style": null,
    "image": "/images/designs/page5-img11.jpeg"
  },
  {
    "design_code": "page5-img12_jpeg",
    "category": null,
    "style": null,
    "image": "/images/designs/page5-img12.jpeg"
  },
  {
    "design_code": "page5-img13_jpeg",
    "category": null,
    "style": null,
    "image": "/images/designs/page5-img13.jpeg"
  },
  {
    "design_code": "page5-img14_jpeg",
    "category": null,
    "style": null,
    "image": "/images/designs/page5-img14.jpeg"
  },
  {
    "design_code": "page5-img15_jpeg",
    "category": null,
    "style": null,
    "image": "/images/designs/page5-img15.jpeg"
  },
  {
    "design_code": "page5-img16_jpeg",
    "category": null,
    "style": null,
    "image": "/images/designs/page5-img16.jpeg"
  },
  {
    "design_code": "page5-img17_jpeg",
    "category": null,
    "style": null,
    "image": "/images/designs/page5-img17.jpeg"
  },
  {
    "design_code": "page5-img18_jpeg",
    "category": null,
    "style": null,
    "image": "/images/designs/page5-img18.jpeg"
  },
  {
    "design_code": "page5-img19_jpeg",
    "category": null,
    "style": null,
    "image": "/images/designs/page5-img19.jpeg"
  },
  {
    "design_code": "page5-img20_jpeg",
    "category": null,
    "style": null,
    "image": "/images/designs/page5-img20.jpeg"
  },
  {
    "design_code": "page6-img1_jpeg",
    "category": null,
    "style": null,
    "image": "/images/designs/page6-img1.jpeg"
  },
  {
    "design_code": "page6-img2_jpeg",
    "category": null,
    "style": null,
    "image": "/images/designs/page6-img2.jpeg"
  },
  {
    "design_code": "page6-img3_jpeg",
    "category": null,
    "style": null,
    "image": "/images/designs/page6-img3.jpeg"
  },
  {
    "design_code": "page6-img4_jpeg",
    "category": null,
    "style": null,
    "image": "/images/designs/page6-img4.jpeg"
  },
  {
    "design_code": "page6-img5_jpeg",
    "category": null,
    "style": null,
    "image": "/images/designs/page6-img5.jpeg"
  },
  {
    "design_code": "page6-img6_jpeg",
    "category": null,
    "style": null,
    "image": "/images/designs/page6-img6.jpeg"
  },
  {
    "design_code": "page6-img7_jpeg",
    "category": null,
    "style": null,
    "image": "/images/designs/page6-img7.jpeg"
  },
  {
    "design_code": "page6-img8_jpeg",
    "category": null,
    "style": null,
    "image": "/images/designs/page6-img8.jpeg"
  },
  {
    "design_code": "page6-img9_jpeg",
    "category": null,
    "style": null,
    "image": "/images/designs/page6-img9.jpeg"
  },
  {
    "design_code": "page6-img10_jpeg",
    "category": null,
    "style": null,
    "image": "/images/designs/page6-img10.jpeg"
  },
  {
    "design_code": "page6-img11_jpeg",
    "category": null,
    "style": null,
    "image": "/images/designs/page6-img11.jpeg"
  },
  {
    "design_code": "page6-img12_jpeg",
    "category": null,
    "style": null,
    "image": "/images/designs/page6-img12.jpeg"
  },
  {
    "design_code": "page6-img13_jpeg",
    "category": null,
    "style": null,
    "image": "/images/designs/page6-img13.jpeg"
  },
  {
    "design_code": "page6-img14_jpeg",
    "category": null,
    "style": null,
    "image": "/images/designs/page6-img14.jpeg"
  },
  {
    "design_code": "page6-img15_jpeg",
    "category": null,
    "style": null,
    "image": "/images/designs/page6-img15.jpeg"
  },
  {
    "design_code": "page6-img16_jpeg",
    "category": null,
    "style": null,
    "image": "/images/designs/page6-img16.jpeg"
  },
  {
    "design_code": "page6-img17_jpeg",
    "category": null,
    "style": null,
    "image": "/images/designs/page6-img17.jpeg"
  },
  {
    "design_code": "page6-img18_jpeg",
    "category": null,
    "style": null,
    "image": "/images/designs/page6-img18.jpeg"
  },
  {
    "design_code": "page6-img19_jpeg",
    "category": null,
    "style": null,
    "image": "/images/designs/page6-img19.jpeg"
  },
  {
    "design_code": "page6-img20_jpeg",
    "category": null,
    "style": null,
    "image": "/images/designs/page6-img20.jpeg"
  },
  {
    "design_code": "page7-img1_jpeg",
    "category": null,
    "style": null,
    "image": "/images/designs/page7-img1.jpeg"
  },
  {
    "design_code": "page7-img2_jpeg",
    "category": null,
    "style": null,
    "image": "/images/designs/page7-img2.jpeg"
  },
  {
    "design_code": "page7-img3_jpeg",
    "category": null,
    "style": null,
    "image": "/images/designs/page7-img3.jpeg"
  },
  {
    "design_code": "page7-img4_jpeg",
    "category": null,
    "style": null,
    "image": "/images/designs/page7-img4.jpeg"
  },
  {
    "design_code": "page7-img5_jpeg",
    "category": null,
    "style": null,
    "image": "/images/designs/page7-img5.jpeg"
  },
  {
    "design_code": "page7-img6_jpeg",
    "category": null,
    "style": null,
    "image": "/images/designs/page7-img6.jpeg"
  },
  {
    "design_code": "page7-img7_jpeg",
    "category": null,
    "style": null,
    "image": "/images/designs/page7-img7.jpeg"
  },
  {
    "design_code": "page7-img8_jpeg",
    "category": null,
    "style": null,
    "image": "/images/designs/page7-img8.jpeg"
  },
  {
    "design_code": "page7-img9_jpeg",
    "category": null,
    "style": null,
    "image": "/images/designs/page7-img9.jpeg"
  },
  {
    "design_code": "page7-img10_jpeg",
    "category": null,
    "style": null,
    "image": "/images/designs/page7-img10.jpeg"
  },
  {
    "design_code": "page7-img11_jpeg",
    "category": null,
    "style": null,
    "image": "/images/designs/page7-img11.jpeg"
  },
  {
    "design_code": "page7-img12_jpeg",
    "category": null,
    "style": null,
    "image": "/images/designs/page7-img12.jpeg"
  },
  {
    "design_code": "page7-img13_jpeg",
    "category": null,
    "style": null,
    "image": "/images/designs/page7-img13.jpeg"
  },
  {
    "design_code": "page7-img14_jpeg",
    "category": null,
    "style": null,
    "image": "/images/designs/page7-img14.jpeg"
  },
  {
    "design_code": "page7-img15_jpeg",
    "category": null,
    "style": null,
    "image": "/images/designs/page7-img15.jpeg"
  },
  {
    "design_code": "page7-img16_jpeg",
    "category": null,
    "style": null,
    "image": "/images/designs/page7-img16.jpeg"
  },
  {
    "design_code": "page7-img17_jpeg",
    "category": null,
    "style": null,
    "image": "/images/designs/page7-img17.jpeg"
  },
  {
    "design_code": "page7-img18_jpeg",
    "category": null,
    "style": null,
    "image": "/images/designs/page7-img18.jpeg"
  },
  {
    "design_code": "page7-img19_jpeg",
    "category": null,
    "style": null,
    "image": "/images/designs/page7-img19.jpeg"
  },
  {
    "design_code": "page8-img1_jpeg",
    "category": null,
    "style": null,
    "image": "/images/designs/page8-img1.jpeg"
  },
  {
    "design_code": "page8-img2_jpeg",
    "category": null,
    "style": null,
    "image": "/images/designs/page8-img2.jpeg"
  },
  {
    "design_code": "page8-img3_jpeg",
    "category": null,
    "style": null,
    "image": "/images/designs/page8-img3.jpeg"
  },
  {
    "design_code": "page8-img4_jpeg",
    "category": null,
    "style": null,
    "image": "/images/designs/page8-img4.jpeg"
  },
  {
    "design_code": "page8-img5_jpeg",
    "category": null,
    "style": null,
    "image": "/images/designs/page8-img5.jpeg"
  },
  {
    "design_code": "page8-img6_jpeg",
    "category": null,
    "style": null,
    "image": "/images/designs/page8-img6.jpeg"
  },
  {
    "design_code": "page8-img7_jpeg",
    "category": null,
    "style": null,
    "image": "/images/designs/page8-img7.jpeg"
  },
  {
    "design_code": "page8-img8_jpeg",
    "category": null,
    "style": null,
    "image": "/images/designs/page8-img8.jpeg"
  },
  {
    "design_code": "page8-img9_jpeg",
    "category": null,
    "style": null,
    "image": "/images/designs/page8-img9.jpeg"
  },
  {
    "design_code": "page8-img10_jpeg",
    "category": null,
    "style": null,
    "image": "/images/designs/page8-img10.jpeg"
  },
  {
    "design_code": "page8-img11_jpeg",
    "category": null,
    "style": null,
    "image": "/images/designs/page8-img11.jpeg"
  },
  {
    "design_code": "page8-img12_jpeg",
    "category": null,
    "style": null,
    "image": "/images/designs/page8-img12.jpeg"
  },
  {
    "design_code": "page8-img13_jpeg",
    "category": null,
    "style": null,
    "image": "/images/designs/page8-img13.jpeg"
  },
  {
    "design_code": "page8-img14_jpeg",
    "category": null,
    "style": null,
    "image": "/images/designs/page8-img14.jpeg"
  },
  {
    "design_code": "page8-img15_jpeg",
    "category": null,
    "style": null,
    "image": "/images/designs/page8-img15.jpeg"
  },
  {
    "design_code": "page8-img16_jpeg",
    "category": null,
    "style": null,
    "image": "/images/designs/page8-img16.jpeg"
  },
  {
    "design_code": "page9-img1_jpeg",
    "category": null,
    "style": null,
    "image": "/images/designs/page9-img1.jpeg"
  },
  {
    "design_code": "page9-img2_jpeg",
    "category": null,
    "style": null,
    "image": "/images/designs/page9-img2.jpeg"
  },
  {
    "design_code": "page9-img3_jpeg",
    "category": null,
    "style": null,
    "image": "/images/designs/page9-img3.jpeg"
  },
  {
    "design_code": "page9-img4_jpeg",
    "category": null,
    "style": null,
    "image": "/images/designs/page9-img4.jpeg"
  },
  {
    "design_code": "page9-img5_png",
    "category": null,
    "style": null,
    "image": "/images/designs/page9-img5.png"
  },
  {
    "design_code": "page9-img6_jpeg",
    "category": null,
    "style": null,
    "image": "/images/designs/page9-img6.jpeg"
  },
  {
    "design_code": "page9-img7_jpeg",
    "category": null,
    "style": null,
    "image": "/images/designs/page9-img7.jpeg"
  },
  {
    "design_code": "page9-img8_jpeg",
    "category": null,
    "style": null,
    "image": "/images/designs/page9-img8.jpeg"
  },
  {
    "design_code": "page9-img9_jpeg",
    "category": null,
    "style": null,
    "image": "/images/designs/page9-img9.jpeg"
  },
  {
    "design_code": "page9-img10_jpeg",
    "category": null,
    "style": null,
    "image": "/images/designs/page9-img10.jpeg"
  },
  {
    "design_code": "page9-img11_jpeg",
    "category": null,
    "style": null,
    "image": "/images/designs/page9-img11.jpeg"
  },
  {
    "design_code": "page9-img12_jpeg",
    "category": null,
    "style": null,
    "image": "/images/designs/page9-img12.jpeg"
  },
  {
    "design_code": "page9-img13_jpeg",
    "category": null,
    "style": null,
    "image": "/images/designs/page9-img13.jpeg"
  },
  {
    "design_code": "page9-img14_jpeg",
    "category": null,
    "style": null,
    "image": "/images/designs/page9-img14.jpeg"
  },
  {
    "design_code": "page9-img15_jpeg",
    "category": null,
    "style": null,
    "image": "/images/designs/page9-img15.jpeg"
  },
  {
    "design_code": "page9-img16_jpeg",
    "category": null,
    "style": null,
    "image": "/images/designs/page9-img16.jpeg"
  },
  {
    "design_code": "page9-img17_jpeg",
    "category": null,
    "style": null,
    "image": "/images/designs/page9-img17.jpeg"
  },
  {
    "design_code": "page9-img18_jpeg",
    "category": null,
    "style": null,
    "image": "/images/designs/page9-img18.jpeg"
  },
  {
    "design_code": "page9-img19_jpeg",
    "category": null,
    "style": null,
    "image": "/images/designs/page9-img19.jpeg"
  },
  {
    "design_code": "page9-img20_jpeg",
    "category": null,
    "style": null,
    "image": "/images/designs/page9-img20.jpeg"
  },
  {
    "design_code": "page10-img1_jpeg",
    "category": null,
    "style": null,
    "image": "/images/designs/page10-img1.jpeg"
  },
  {
    "design_code": "page10-img2_jpeg",
    "category": null,
    "style": null,
    "image": "/images/designs/page10-img2.jpeg"
  },
  {
    "design_code": "page10-img3_jpeg",
    "category": null,
    "style": null,
    "image": "/images/designs/page10-img3.jpeg"
  },
  {
    "design_code": "page10-img4_jpeg",
    "category": null,
    "style": null,
    "image": "/images/designs/page10-img4.jpeg"
  },
  {
    "design_code": "page10-img5_jpeg",
    "category": null,
    "style": null,
    "image": "/images/designs/page10-img5.jpeg"
  },
  {
    "design_code": "page10-img6_jpeg",
    "category": null,
    "style": null,
    "image": "/images/designs/page10-img6.jpeg"
  },
  {
    "design_code": "page10-img7_jpeg",
    "category": null,
    "style": null,
    "image": "/images/designs/page10-img7.jpeg"
  },
  {
    "design_code": "page10-img8_jpeg",
    "category": null,
    "style": null,
    "image": "/images/designs/page10-img8.jpeg"
  },
  {
    "design_code": "page10-img9_jpeg",
    "category": null,
    "style": null,
    "image": "/images/designs/page10-img9.jpeg"
  },
  {
    "design_code": "page10-img10_jpeg",
    "category": null,
    "style": null,
    "image": "/images/designs/page10-img10.jpeg"
  },
  {
    "design_code": "page10-img11_jpeg",
    "category": null,
    "style": null,
    "image": "/images/designs/page10-img11.jpeg"
  },
  {
    "design_code": "page10-img12_jpeg",
    "category": null,
    "style": null,
    "image": "/images/designs/page10-img12.jpeg"
  },
  {
    "design_code": "page10-img13_jpeg",
    "category": null,
    "style": null,
    "image": "/images/designs/page10-img13.jpeg"
  },
  {
    "design_code": "page10-img14_jpeg",
    "category": null,
    "style": null,
    "image": "/images/designs/page10-img14.jpeg"
  },
  {
    "design_code": "page10-img15_jpeg",
    "category": null,
    "style": null,
    "image": "/images/designs/page10-img15.jpeg"
  },
  {
    "design_code": "page10-img16_jpeg",
    "category": null,
    "style": null,
    "image": "/images/designs/page10-img16.jpeg"
  },
  {
    "design_code": "page10-img17_jpeg",
    "category": null,
    "style": null,
    "image": "/images/designs/page10-img17.jpeg"
  },
  {
    "design_code": "page10-img18_jpeg",
    "category": null,
    "style": null,
    "image": "/images/designs/page10-img18.jpeg"
  },
  {
    "design_code": "page10-img19_jpeg",
    "category": null,
    "style": null,
    "image": "/images/designs/page10-img19.jpeg"
  },
  {
    "design_code": "page10-img20_jpeg",
    "category": null,
    "style": null,
    "image": "/images/designs/page10-img20.jpeg"
  },
  {
    "design_code": "page11-img1_jpeg",
    "category": null,
    "style": null,
    "image": "/images/designs/page11-img1.jpeg"
  },
  {
    "design_code": "page11-img2_jpeg",
    "category": null,
    "style": null,
    "image": "/images/designs/page11-img2.jpeg"
  },
  {
    "design_code": "page11-img3_jpeg",
    "category": null,
    "style": null,
    "image": "/images/designs/page11-img3.jpeg"
  },
  {
    "design_code": "page11-img4_jpeg",
    "category": null,
    "style": null,
    "image": "/images/designs/page11-img4.jpeg"
  },
  {
    "design_code": "page11-img5_jpeg",
    "category": null,
    "style": null,
    "image": "/images/designs/page11-img5.jpeg"
  },
  {
    "design_code": "page11-img6_jpeg",
    "category": null,
    "style": null,
    "image": "/images/designs/page11-img6.jpeg"
  },
  {
    "design_code": "page11-img7_jpeg",
    "category": null,
    "style": null,
    "image": "/images/designs/page11-img7.jpeg"
  },
  {
    "design_code": "page11-img8_jpeg",
    "category": null,
    "style": null,
    "image": "/images/designs/page11-img8.jpeg"
  },
  {
    "design_code": "page11-img9_jpeg",
    "category": null,
    "style": null,
    "image": "/images/designs/page11-img9.jpeg"
  },
  {
    "design_code": "page11-img10_jpeg",
    "category": null,
    "style": null,
    "image": "/images/designs/page11-img10.jpeg"
  },
  {
    "design_code": "page11-img11_jpeg",
    "category": null,
    "style": null,
    "image": "/images/designs/page11-img11.jpeg"
  },
  {
    "design_code": "page11-img12_png",
    "category": null,
    "style": null,
    "image": "/images/designs/page11-img12.png"
  },
  {
    "design_code": "page11-img13_jpeg",
    "category": null,
    "style": null,
    "image": "/images/designs/page11-img13.jpeg"
  },
  {
    "design_code": "page11-img14_jpeg",
    "category": null,
    "style": null,
    "image": "/images/designs/page11-img14.jpeg"
  },
  {
    "design_code": "page11-img15_jpeg",
    "category": null,
    "style": null,
    "image": "/images/designs/page11-img15.jpeg"
  },
  {
    "design_code": "page11-img16_jpeg",
    "category": null,
    "style": null,
    "image": "/images/designs/page11-img16.jpeg"
  },
  {
    "design_code": "page11-img17_jpeg",
    "category": null,
    "style": null,
    "image": "/images/designs/page11-img17.jpeg"
  },
  {
    "design_code": "page11-img18_jpeg",
    "category": null,
    "style": null,
    "image": "/images/designs/page11-img18.jpeg"
  },
  {
    "design_code": "page11-img19_jpeg",
    "category": null,
    "style": null,
    "image": "/images/designs/page11-img19.jpeg"
  },
  {
    "design_code": "page11-img20_jpeg",
    "category": null,
    "style": null,
    "image": "/images/designs/page11-img20.jpeg"
  },
  {
    "design_code": "page11-img21_jpeg",
    "category": null,
    "style": null,
    "image": "/images/designs/page11-img21.jpeg"
  },
  {
    "design_code": "page12-img1_jpeg",
    "category": null,
    "style": null,
    "image": "/images/designs/page12-img1.jpeg"
  },
  {
    "design_code": "page12-img2_jpeg",
    "category": null,
    "style": null,
    "image": "/images/designs/page12-img2.jpeg"
  },
  {
    "design_code": "page12-img3_jpeg",
    "category": null,
    "style": null,
    "image": "/images/designs/page12-img3.jpeg"
  },
  {
    "design_code": "page13-img1_jpeg",
    "category": null,
    "style": null,
    "image": "/images/designs/page13-img1.jpeg"
  }
]